{
  "version": "7",
  "dialect": "postgresql",
  "entries": [
    {
      "idx": 0,
      "version": "7",
      "when": 1754471281151,
      "tag": "0000_loud_stellaris",
      "breakpoints": true
    },
    {
      "idx": 1,
      "version": "7",
      "when": 1754484505984,
      "tag": "0001_calm_ben_grimm",
      "breakpoints": true
    },
    {
      "idx": 2,
      "version": "7",
      "when": 1754494688911,
      "tag": "0002_chilly_moon_knight",
      "breakpoints": true
    },
    {
      "idx": 3,
      "version": "7",
      "when": 1754495727564,
      "tag": "0003_familiar_lilandra",
      "breakpoints": true
    }
  ]
}